cindergrace_netman/__init__.py
cindergrace_netman/checks.py
cindergrace_netman/cli.py
cindergrace_netman/net.py
cindergrace_netman/state.py
cindergrace_netman/tray.py
cindergrace_netman/ui.py
cindergrace_netman-0.1.3.dist-info/licenses/LICENSE
cindergrace_netman-0.1.3.dist-info/METADATA
cindergrace_netman-0.1.3.dist-info/WHEEL
cindergrace_netman-0.1.3.dist-info/entry_points.txt
cindergrace_netman-0.1.3.dist-info/top_level.txt
cindergrace_netman-0.1.3.dist-info/RECORD
