Metadata-Version: 2.4
Name: cindergrace-netman
Version: 0.1.3
Summary: Network bandwidth management tool for Linux
Author: goettemar
License-Expression: PolyForm-Noncommercial-1.0.0
Project-URL: Homepage, https://github.com/goettemar/cindergrace_netman
Project-URL: Repository, https://github.com/goettemar/cindergrace_netman
Project-URL: Issues, https://github.com/goettemar/cindergrace_netman/issues
Keywords: network,bandwidth,traffic-control,linux,tc,qdisc,gradio
Classifier: Development Status :: 4 - Beta
Classifier: Intended Audience :: System Administrators
Classifier: Intended Audience :: Developers
Classifier: Topic :: System :: Networking
Classifier: Topic :: System :: Systems Administration
Classifier: Operating System :: POSIX :: Linux
Classifier: Environment :: Web Environment
Classifier: Programming Language :: Python :: 3
Classifier: Programming Language :: Python :: 3.10
Classifier: Programming Language :: Python :: 3.11
Classifier: Programming Language :: Python :: 3.12
Requires-Python: >=3.10
License-File: LICENSE
Requires-Dist: gradio>=5.0
Requires-Dist: gradio-i18n>=0.0.12
Requires-Dist: pystray>=0.19
Requires-Dist: pillow>=10.0
Requires-Dist: pyyaml>=6.0
Provides-Extra: dev
Requires-Dist: pytest>=7.0; extra == "dev"
Requires-Dist: pytest-cov>=4.0; extra == "dev"
Requires-Dist: ruff>=0.1.0; extra == "dev"
Dynamic: license-file
